ArducamEvkSDK.so
ArducamEvkSDK.pyi
ArducamEvkSDK.libs/libarducam_config_parser-20eb9161.so
ArducamEvkSDK-1.0.8.dist-info/METADATA
ArducamEvkSDK-1.0.8.dist-info/WHEEL
ArducamEvkSDK-1.0.8.dist-info/RECORD
ArducamEvkSDK-1.0.8.dist-info/top_level.txt
