Metadata-Version: 2.2
Name: ArducamEvkSDK
Version: 1.0.8
Summary: A c project using pybind11
Requires-Python: >=2.7
Dynamic: requires-python
Dynamic: summary
